tlsprofiler/__init__.py
tlsprofiler/cli.py
tlsprofiler/comparator.py
tlsprofiler/tlsprofiler_result.py
tlsprofiler/utils.py
tlsprofiler-2.1.dist-info/LICENSE
tlsprofiler-2.1.dist-info/METADATA
tlsprofiler-2.1.dist-info/WHEEL
tlsprofiler-2.1.dist-info/entry_points.txt
tlsprofiler-2.1.dist-info/RECORD
