Metadata-Version: 2.1
Name: tlsprofiler
Version: 2.1
Summary: This tool/library can be used to compare the configuration of a TLS server to the Mozilla TLS configuration recommendations.
License: AGPL-3.0
Author: Daniel Fett
Author-email: mail@danielfett.de
Requires-Python: >=3.7,<4.0
Classifier: License :: OSI Approved :: GNU Affero General Public License v3
Classifier: Programming Language :: Python :: 3
Classifier: Programming Language :: Python :: 3.7
Classifier: Programming Language :: Python :: 3.8
Classifier: Programming Language :: Python :: 3.9
Classifier: Programming Language :: Python :: 3.10
Classifier: Programming Language :: Python :: 3.11
Requires-Dist: cryptography (>=2.8)
Requires-Dist: nassl (>=3.1.0,<4.0.0)
Requires-Dist: requests (>=2.31.0,<3.0.0)
Requires-Dist: sslyze (>=3.1.0,<4.0.0)
Requires-Dist: tabulate (>=0.9.0,<0.10.0)
